{
  "slug": "client-churn-dropped-by",
  "locale": "es",
  "collectionType": "case-study-results",
  "name": "La pérdida de clientes se redujo",
  "collection_id": "689107d6d9f5f1e22ab2c39e",
  "locale_id": "68a473ac6f18f13d93fc8275",
  "item_id": "68a7d65fd8866d7ee3f5ce72",
  "archived": false,
  "draft": false,
  "created_on": "Fri Aug 22 2025 02:30:55 GMT+0000 (Coordinated Universal Time)",
  "updated_on": "Fri Aug 22 2025 02:30:55 GMT+0000 (Coordinated Universal Time)",
  "published_on": "Fri Aug 22 2025 03:09:46 GMT+0000 (Coordinated Universal Time)",
  "value": "0.5",
  "icon": "https://cdn.prod.website-files.com/6877df595609c1d0ca9e8c30/68a4c1f3c048b7c6b61adf7d_67057419c39f9db8c342c149_Customer%2520chrun%2520icon.png",
  "seo": {
    "title": "La pérdida de clientes se redujo",
    "description": "__MISSING__",
    "canonical": "https://www.synup.com/es/case-study-results/client-churn-dropped-by",
    "ogImage": null
  }
}