{
  "slug": "increased-phone-calls-to-collision-center-by",
  "locale": "es",
  "collectionType": "case-study-results",
  "name": "Las llamadas telefónicas al centro de colisiones aumentaron en",
  "collection_id": "689107d6d9f5f1e22ab2c39e",
  "locale_id": "68a473ac6f18f13d93fc8275",
  "item_id": "68a7d65f9c5730b36418e006",
  "archived": false,
  "draft": false,
  "created_on": "Fri Aug 22 2025 02:30:55 GMT+0000 (Coordinated Universal Time)",
  "updated_on": "Fri Aug 22 2025 02:30:55 GMT+0000 (Coordinated Universal Time)",
  "published_on": "Fri Aug 22 2025 03:09:46 GMT+0000 (Coordinated Universal Time)",
  "value": "0.82",
  "icon": "https://cdn.prod.website-files.com/6877df595609c1d0ca9e8c30/68a4c1f5b02468dcca3f64c4_6705683aeb8af7163a4f7743_Phone%2520icon.png",
  "seo": {
    "title": "Las llamadas telefónicas al centro de colisiones aumentaron en",
    "description": "__MISSING__",
    "canonical": "https://www.synup.com/es/case-study-results/increased-phone-calls-to-collision-center-by",
    "ogImage": null
  }
}