{
  "slug": "review-generation-via-sms-email-3",
  "locale": "de",
  "collectionType": "comparison-table-rows",
  "name": "CRM Integration for Review Campaigns",
  "collection_id": "6891dac917be53a8753023b6",
  "locale_id": "689b745049dcf9cf63f57d03",
  "item_id": "68cd1afbdf7b04e58e4a8247",
  "archived": false,
  "draft": false,
  "created_on": "Fri Sep 19 2025 08:57:31 GMT+0000 (Coordinated Universal Time)",
  "updated_on": "Fri Sep 19 2025 09:11:12 GMT+0000 (Coordinated Universal Time)",
  "published_on": "Sat Sep 20 2025 07:00:16 GMT+0000 (Coordinated Universal Time)",
  "sub_description": "Integrations with 50+ CRM/POS tools to automate review campaigns",
  "first_col": "Y",
  "second_col": "N",
  "select_table_category": "agency-management",
  "list_order": null,
  "select_pages": "gohighlevel-alternative",
  "seo": {
    "title": "CRM Integration for Review Campaigns",
    "description": "__MISSING__",
    "canonical": "https://www.synup.com/de/comparison-table-rows/crm-integration-for-review-campaigns",
    "ogImage": null
  }
}